cebra/__init__.py
cebra/__main__.py
cebra/config.py
cebra/grid_search.py
cebra/helper.py
cebra/io.py
cebra/registry.py
cebra/attribution/__init__.py
cebra/attribution/_jacobian.py
cebra/attribution/attribution_models.py
cebra/attribution/jacobian_attribution.py
cebra/data/__init__.py
cebra/data/assets.py
cebra/data/base.py
cebra/data/datasets.py
cebra/data/datatypes.py
cebra/data/helper.py
cebra/data/load.py
cebra/data/masking.py
cebra/data/multi_session.py
cebra/data/multiobjective.py
cebra/data/single_session.py
cebra/datasets/__init__.py
cebra/datasets/demo.py
cebra/datasets/gaussian_mixture.py
cebra/datasets/generate_synthetic_data.py
cebra/datasets/hippocampus.py
cebra/datasets/make_neuropixel.py
cebra/datasets/monkey_reaching.py
cebra/datasets/poisson.py
cebra/datasets/save_dataset.py
cebra/datasets/synthetic_data.py
cebra/datasets/allen/__init__.py
cebra/datasets/allen/ca_movie.py
cebra/datasets/allen/ca_movie_decoding.py
cebra/datasets/allen/combined.py
cebra/datasets/allen/make_neuropixel.py
cebra/datasets/allen/neuropixel_movie.py
cebra/datasets/allen/neuropixel_movie_decoding.py
cebra/datasets/allen/single_session_ca.py
cebra/distributions/__init__.py
cebra/distributions/base.py
cebra/distributions/continuous.py
cebra/distributions/discrete.py
cebra/distributions/index.py
cebra/distributions/mixed.py
cebra/distributions/multisession.py
cebra/integrations/__init__.py
cebra/integrations/decoders.py
cebra/integrations/deeplabcut.py
cebra/integrations/matplotlib.py
cebra/integrations/plotly.py
cebra/integrations/sklearn/__init__.py
cebra/integrations/sklearn/cebra.py
cebra/integrations/sklearn/dataset.py
cebra/integrations/sklearn/decoder.py
cebra/integrations/sklearn/helpers.py
cebra/integrations/sklearn/metrics.py
cebra/integrations/sklearn/utils.py
cebra/models/__init__.py
cebra/models/criterions.py
cebra/models/jacobian_regularizer.py
cebra/models/layers.py
cebra/models/model.py
cebra/models/multicriterions.py
cebra/models/multiobjective.py
cebra-0.6.0.dist-info/licenses/LICENSE.md
cebra-0.6.0.dist-info/METADATA
cebra-0.6.0.dist-info/WHEEL
cebra-0.6.0.dist-info/top_level.txt
cebra-0.6.0.dist-info/RECORD
