Metadata-Version: 2.4
Name: cebra
Version: 0.6.0
Summary: Consistent Embeddings of high-dimensional Recordings using Auxiliary variables
Home-page: https://github.com/AdaptiveMotorControlLab/CEBRA
Author: file: AUTHORS.md
Author-email: stes@hey.com, mackenzie@post.harvard.edu
License: Apache-2.0
Project-URL: Bug Tracker, https://github.com/AdaptiveMotorControlLab/CEBRA/issues
Classifier: Development Status :: 4 - Beta
Classifier: Environment :: GPU :: NVIDIA CUDA
Classifier: Intended Audience :: Science/Research
Classifier: Operating System :: OS Independent
Classifier: Programming Language :: Python :: 3
Classifier: Topic :: Scientific/Engineering :: Artificial Intelligence
Requires-Python: >=3.10
License-File: LICENSE.md
Requires-Dist: joblib
Requires-Dist: numpy<2.0; platform_system == "Windows"
Requires-Dist: numpy; platform_system != "Windows" and python_version >= "3.10"
Requires-Dist: literate-dataclasses
Requires-Dist: scikit-learn
Requires-Dist: scipy
Requires-Dist: torch>=2.4.0
Requires-Dist: tqdm
Requires-Dist: matplotlib
Requires-Dist: requests
Provides-Extra: datasets
Requires-Dist: h5py; extra == "datasets"
Requires-Dist: pandas; extra == "datasets"
Requires-Dist: hdf5storage; extra == "datasets"
Requires-Dist: openpyxl; extra == "datasets"
Requires-Dist: tables; extra == "datasets"
Provides-Extra: integrations
Requires-Dist: pandas; extra == "integrations"
Requires-Dist: plotly; extra == "integrations"
Requires-Dist: seaborn; extra == "integrations"
Requires-Dist: captum; extra == "integrations"
Requires-Dist: cvxpy; extra == "integrations"
Requires-Dist: scikit-image; extra == "integrations"
Provides-Extra: docs
Requires-Dist: sphinx; extra == "docs"
Requires-Dist: sphinx-gallery; extra == "docs"
Requires-Dist: docutils; extra == "docs"
Requires-Dist: pydata-sphinx-theme; extra == "docs"
Requires-Dist: sphinx_autodoc_typehints; extra == "docs"
Requires-Dist: sphinx_copybutton; extra == "docs"
Requires-Dist: sphinx_tabs; extra == "docs"
Requires-Dist: sphinx_design; extra == "docs"
Requires-Dist: sphinx_togglebutton; extra == "docs"
Requires-Dist: nbsphinx; extra == "docs"
Requires-Dist: nbconvert; extra == "docs"
Requires-Dist: ipykernel; extra == "docs"
Requires-Dist: matplotlib; extra == "docs"
Requires-Dist: pandas; extra == "docs"
Requires-Dist: seaborn; extra == "docs"
Requires-Dist: scikit-learn; extra == "docs"
Provides-Extra: demos
Requires-Dist: ipykernel; extra == "demos"
Requires-Dist: jupyter; extra == "demos"
Requires-Dist: nbconvert; extra == "demos"
Provides-Extra: dev
Requires-Dist: pylint; extra == "dev"
Requires-Dist: toml; extra == "dev"
Requires-Dist: yapf; extra == "dev"
Requires-Dist: black; extra == "dev"
Requires-Dist: isort; extra == "dev"
Requires-Dist: toml; extra == "dev"
Requires-Dist: coverage; extra == "dev"
Requires-Dist: pytest; extra == "dev"
Requires-Dist: pytest-benchmark; extra == "dev"
Requires-Dist: pytest-xdist; extra == "dev"
Requires-Dist: pytest-timeout; extra == "dev"
Requires-Dist: pytest-sphinx; extra == "dev"
Requires-Dist: licenseheaders; extra == "dev"
Requires-Dist: interrogate; extra == "dev"
Requires-Dist: codespell; extra == "dev"
Requires-Dist: cffconvert; extra == "dev"
Dynamic: license-file
